{"bill": {"@bill-stage": "Introduced-in-Senate", "@public-private": "public", "legis-body": {"#tail": "\n", "@style": "OLC", "section": [{"@section-type": "section-one", "#tail": "\n    ", "text": {"#tail": "\n\t\t", "quote": {"short-title": {"#tail": "\n        ", "#text": "Corporal Michael J. Crescenz Act of\n\t\t\t 2013"}, "#tail": ".", "#text": "\n          "}, "#text": "This Act may be cited as the\n\t\t\t ", "@display-inline": "no-display-inline"}, "enum": {"#tail": "\n      ", "#text": "1."}, "header": {"#tail": "\n      ", "#text": "Short title"}, "#text": "\n      ", "@id": "id6CD0A00704444605870A0393513EB4E5"}, {"@section-type": "subsequent-section", "#tail": "\n  ", "enum": {"#tail": "\n      ", "#text": "2."}, "header": {"#tail": "\n\t\t\t", "#text": "Corporal Michael J.\n\t\t\t Crescenz Department of Veterans Affairs Medical Center"}, "subsection": [{"#tail": "\n      ", "text": {"#tail": "\n\t\t\t", "{http://namespaces.cato.org/catoxml}entity-ref": {"#tail": " located at 3900 Woodland Avenue in Philadelphia, Pennsylvania,\n\t\t\t shall after the date of the enactment of this Act be known and designated as\n\t\t\t the ", "@entity-type": "federal-body", "#text": "Department of\n\t\t\t Veterans Affairs", "@entity-id": "3600"}, "quote": {"#tail": ".", "{http://namespaces.cato.org/catoxml}entity-ref": {"#tail": " Medical\n\t\t\t Center", "@entity-type": "federal-body", "#text": "Department of Veterans Affairs", "@entity-id": "3600"}, "#text": "Corporal Michael J. Crescenz "}, "#text": "The medical center of the ", "@display-inline": "yes-display-inline"}, "enum": {"#tail": "\n        ", "#text": "(a)"}, "header": {"#tail": "\n        ", "#text": "Designation"}, "#text": "\n        ", "@id": "H1A01BAA97C1347F48590ED604C411410"}, {"#tail": "\n    ", "text": {"#tail": "\n\t\t\t", "{http://namespaces.cato.org/catoxml}entity-ref": [{"#tail": " shall be\n\t\t\t considered to be a reference to the Corporal Michael J. Crescenz ", "@entity-type": "act", "#text": "subsection (a)", "@value": "Corporal Michael J. Crescenz Act of 2013/s:2/ss:a", "@proposed": "true"}, {"#tail": " Medical Center.", "@entity-type": "federal-body", "#text": "Department of\n\t\t\t Veterans Affairs", "@entity-id": "3600"}], "#text": "Any\n\t\t\t reference in any law, regulation, map, document, paper, or other record of the\n\t\t\t United States to the medical center referred to in "}, "enum": {"#tail": "\n        ", "#text": "(b)"}, "header": {"#tail": "\n        ", "#text": "References"}, "#text": "\n        ", "@id": "H1E2F1E4A175A44C6990E49506FB2C3C1"}], "#text": "\n      ", "@id": "id254670FFD93C4910AC8FAC63D785D011"}], "#text": "\n\t\t", "@id": "HB2024FA29A904660B19C357684CB03FB"}, "#text": "\n\t", "form": {"current-chamber": {"#tail": "\n\t\t", "#text": "IN THE SENATE OF THE UNITED STATES"}, "#text": "\n\t\t", "congress": {"#tail": "\n\t\t", "#text": "113th CONGRESS"}, "#tail": "\n\t", "legis-num": {"#tail": "\n\t\t", "#text": "S. 229"}, "official-title": {"#tail": "\n\t", "quote": {"#tail": ". ", "#text": "Corporal Michael J. Crescenz Department of Veterans Affairs\n\t\t  Medical Center"}, "#text": "To designate the medical center of the Department of\n\t\t  Veterans Affairs located at 3900 Woodland Avenue in Philadelphia, Pennsylvania,\n\t\t  as the "}, "session": {"#tail": "\n\t\t", "#text": "1st Session"}, "distribution-code": {"#tail": "\n\t\t", "@display": "yes", "#text": "II"}, "action": {"action-date": {"#tail": "\n\t\t\t", "@date": "20130207", "#text": "February 7, 2013"}, "#tail": "\n\t\t", "action-desc": {"#tail": "\n\t\t", "#text": "\n        ", "committee-name": {"#tail": "\n      ", "@committee-id": "SSVA00", "#text": "Committee on Veterans'\n\t\t\t Affairs"}, "sponsor": {"#tail": " (for himself\n\t\t\t and ", "#text": "Mr. Toomey", "@name-id": "S351"}, "cosponsor": {"#tail": ") introduced the following\n\t\t\t bill; which was read twice and referred to the\n\t\t\t ", "#text": "Mr. Casey", "@name-id": "S309"}}, "#text": "\n\t\t\t"}, "legis-type": {"#tail": "\n\t\t", "#text": "A BILL"}}}}